build_scripts/installer-version.py
mozilla-ca/__init__.py
mozilla-ca/cacert.pem
salvia/__init__.py
salvia/py.typed
salvia/pyinstaller.spec
salvia/clvm/singleton.py
salvia/clvm/spend_sim.py
salvia/cmds/__init__.py
salvia/cmds/configure.py
salvia/cmds/farm.py
salvia/cmds/farm_funcs.py
salvia/cmds/init.py
salvia/cmds/init_funcs.py
salvia/cmds/keys.py
salvia/cmds/keys_funcs.py
salvia/cmds/netspace.py
salvia/cmds/netspace_funcs.py
salvia/cmds/passphrase.py
salvia/cmds/passphrase_funcs.py
salvia/cmds/plotnft.py
salvia/cmds/plotnft_funcs.py
salvia/cmds/plots.py
salvia/cmds/salvia.py
salvia/cmds/show.py
salvia/cmds/start.py
salvia/cmds/start_funcs.py
salvia/cmds/stop.py
salvia/cmds/units.py
salvia/cmds/wallet.py
salvia/cmds/wallet_funcs.py
salvia/consensus/__init__.py
salvia/consensus/block_body_validation.py
salvia/consensus/block_creation.py
salvia/consensus/block_header_validation.py
salvia/consensus/block_record.py
salvia/consensus/block_rewards.py
salvia/consensus/block_root_validation.py
salvia/consensus/blockchain.py
salvia/consensus/blockchain_interface.py
salvia/consensus/coinbase.py
salvia/consensus/condition_costs.py
salvia/consensus/constants.py
salvia/consensus/cost_calculator.py
salvia/consensus/default_constants.py
salvia/consensus/deficit.py
salvia/consensus/difficulty_adjustment.py
salvia/consensus/find_fork_point.py
salvia/consensus/full_block_to_block_record.py
salvia/consensus/get_block_challenge.py
salvia/consensus/make_sub_epoch_summary.py
salvia/consensus/multiprocess_validation.py
salvia/consensus/network_type.py
salvia/consensus/pos_quality.py
salvia/consensus/pot_iterations.py
salvia/consensus/vdf_info_computation.py
salvia/daemon/__init__.py
salvia/daemon/client.py
salvia/daemon/keychain_proxy.py
salvia/daemon/keychain_server.py
salvia/daemon/server.py
salvia/daemon/windows_signal.py
salvia/farmer/__init__.py
salvia/farmer/farmer.py
salvia/farmer/farmer_api.py
salvia/full_node/__init__.py
salvia/full_node/block_store.py
salvia_blockchain-0.6.7.dev2.dist-info/LICENSE
salvia_blockchain-0.6.7.dev2.dist-info/METADATA
salvia_blockchain-0.6.7.dev2.dist-info/WHEEL
salvia_blockchain-0.6.7.dev2.dist-info/entry_points.txt
salvia_blockchain-0.6.7.dev2.dist-info/top_level.txt
salvia_blockchain-0.6.7.dev2.dist-info/RECORD
